[{
  "summary": [
    {
      "distance": 11110,
      "duration": 11191,
      "steps": 18459,
      "group": "walking",
      "activity": "walking"
    },
    {
      "distance": 32089,
      "duration": 4036,
      "group": "transport",
      "activity": "transport"
    }
  ],
  "segments": [
    {
      "startTime": "20160327T193059-0700",
      "lastUpdate": "20160328T181450Z",
      "activities": [
        {
          "startTime": "20160328T002710-0700",
          "manual": false,
          "distance": 126,
          "duration": 128,
          "trackPoints": [],
          "steps": 168,
          "endTime": "20160328T002918-0700",
          "group": "walking",
          "activity": "walking"
        },
        {
          "startTime": "20160328T093944-0700",
          "manual": false,
          "distance": 49,
          "duration": 97,
          "trackPoints": [],
          "steps": 89,
          "endTime": "20160328T094121-0700",
          "group": "walking",
          "activity": "walking"
        },
        {
          "startTime": "20160328T100000-0700",
          "manual": false,
          "distance": 185,
          "duration": 171,
          "trackPoints": [],
          "steps": 246,
          "endTime": "20160328T100251-0700",
          "group": "walking",
          "activity": "walking"
        }
      ],
      "place": {
        "id": 52989451,
        "location": {
          "lon": -123.0955654948,
          "lat": 49.2609911813
        },
        "name": "Home",
        "type": "home"
      },
      "endTime": "20160328T100413-0700",
      "type": "place"
    },
    {
      "startTime": "20160328T100413-0700",
      "lastUpdate": "20160328T181450Z",
      "activities": [{
        "startTime": "20160328T100413-0700",
        "manual": false,
        "distance": 661,
        "duration": 386,
        "trackPoints": [
          {
            "time": "20160328T100413-0700",
            "lon": -123.0955654948,
            "lat": 49.2609911813
          },
          {
            "time": "20160328T100455-0700",
            "lon": -123.0966269768,
            "lat": 49.2622818278
          },
          {
            "time": "20160328T100537-0700",
            "lon": -123.0972640798,
            "lat": 49.2623744103
          },
          {
            "time": "20160328T100603-0700",
            "lon": -123.0976643399,
            "lat": 49.2624340672
          },
          {
            "time": "20160328T100919-0700",
            "lon": -123.1007484091,
            "lat": 49.2627066007
          },
          {
            "time": "20160328T100940-0700",
            "lon": -123.1009981505,
            "lat": 49.2627534611
          },
          {
            "time": "20160328T101039-0700",
            "lon": -123.100795,
            "lat": 49.2635748
          }
        ],
        "steps": 709,
        "endTime": "20160328T101039-0700",
        "group": "walking",
        "activity": "walking"
      }],
      "endTime": "20160328T101039-0700",
      "type": "move"
    },
    {
      "startTime": "20160328T101040-0700",
      "lastUpdate": "20160328T211443Z",
      "activities": [{
        "startTime": "20160328T101040-0700",
        "manual": false,
        "distance": 6,
        "duration": 9,
        "trackPoints": [],
        "steps": 12,
        "endTime": "20160328T101049-0700",
        "group": "walking",
        "activity": "walking"
      }],
      "place": {
        "id": 21847350,
        "location": {
          "lon": -123.100795,
          "lat": 49.2635748
        },
        "name": "The Wallflower",
        "foursquareId": "4ac9482df964a52086bf20e3",
        "type": "foursquare"
      },
      "endTime": "20160328T110647-0700",
      "type": "place"
    },
    {
      "startTime": "20160328T110647-0700",
      "lastUpdate": "20160328T211443Z",
      "activities": [{
        "startTime": "20160328T110647-0700",
        "manual": false,
        "distance": 576,
        "duration": 597,
        "trackPoints": [
          {
            "time": "20160328T110647-0700",
            "lon": -123.100795,
            "lat": 49.2635748
          },
          {
            "time": "20160328T110716-0700",
            "lon": -123.1005566827,
            "lat": 49.2633510535
          },
          {
            "time": "20160328T110749-0700",
            "lon": -123.1003187671,
            "lat": 49.2630869031
          },
          {
            "time": "20160328T110810-0700",
            "lon": -123.0999177715,
            "lat": 49.2629725959
          },
          {
            "time": "20160328T110832-0700",
            "lon": -123.0995851927,
            "lat": 49.2628926844
          },
          {
            "time": "20160328T110926-0700",
            "lon": -123.0987810876,
            "lat": 49.262751647
          },
          {
            "time": "20160328T110950-0700",
            "lon": -123.0983272018,
            "lat": 49.2626959619
          },
          {
            "time": "20160328T111307-0700",
            "lon": -123.096571885,
            "lat": 49.2618854565
          },
          {
            "time": "20160328T111345-0700",
            "lon": -123.0962666635,
            "lat": 49.2617421317
          },
          {
            "time": "20160328T111418-0700",
            "lon": -123.0961004747,
            "lat": 49.2615095429
          },
          {
            "time": "20160328T111441-0700",
            "lon": -123.0960120959,
            "lat": 49.2613463461
          },
          {
            "time": "20160328T111501-0700",
            "lon": -123.0959303678,
            "lat": 49.2612013873
          },
          {
            "time": "20160328T111542-0700",
            "lon": -123.0957816635,
            "lat": 49.2609806981
          },
          {
            "time": "20160328T111603-0700",
            "lon": -123.0957518839,
            "lat": 49.2609713514
          },
          {
            "time": "20160328T111623-0700",
            "lon": -123.0957012901,
            "lat": 49.2609713308
          },
          {
            "time": "20160328T111644-0700",
            "lon": -123.0954408406,
            "lat": 49.2609939412
          }
        ],
        "steps": 1051,
        "endTime": "20160328T111644-0700",
        "group": "walking",
        "activity": "walking"
      }],
      "endTime": "20160328T111644-0700",
      "type": "move"
    },
    {
      "startTime": "20160328T111644-0700",
      "lastUpdate": "20160328T211443Z",
      "activities": [{
        "startTime": "20160328T111644-0700",
        "manual": false,
        "distance": 4,
        "duration": 4,
        "trackPoints": [],
        "steps": 8,
        "endTime": "20160328T111648-0700",
        "group": "walking",
        "activity": "walking"
      }],
      "place": {
        "id": 8806369,
        "location": {
          "lon": -123.0954408406,
          "lat": 49.2609939412
        },
        "name": "Home",
        "type": "home"
      },
      "endTime": "20160328T113040-0700",
      "type": "place"
    },
    {
      "startTime": "20160328T113040-0700",
      "lastUpdate": "20160328T211443Z",
      "activities": [{
        "startTime": "20160328T113040-0700",
        "manual": false,
        "distance": 866,
        "duration": 687,
        "trackPoints": [
          {
            "time": "20160328T113040-0700",
            "lon": -123.0954408406,
            "lat": 49.2609939412
          },
          {
            "time": "20160328T113104-0700",
            "lon": -123.0953686933,
            "lat": 49.2610793884
          },
          {
            "time": "20160328T113127-0700",
            "lon": -123.0954269371,
            "lat": 49.2610642586
          },
          {
            "time": "20160328T113144-0700",
            "lon": -123.0954013291,
            "lat": 49.2610812603
          },
          {
            "time": "20160328T113159-0700",
            "lon": -123.0953310924,
            "lat": 49.2611083615
          },
          {
            "time": "20160328T113220-0700",
            "lon": -123.0951168166,
            "lat": 49.2611793277
          },
          {
            "time": "20160328T113241-0700",
            "lon": -123.0948101087,
            "lat": 49.261293268
          },
          {
            "time": "20160328T113305-0700",
            "lon": -123.0943894023,
            "lat": 49.2614162963
          },
          {
            "time": "20160328T113347-0700",
            "lon": -123.093441759,
            "lat": 49.2615085634
          },
          {
            "time": "20160328T113403-0700",
            "lon": -123.0931434952,
            "lat": 49.2615324545
          },
          {
            "time": "20160328T113426-0700",
            "lon": -123.0927008839,
            "lat": 49.2615789397
          },
          {
            "time": "20160328T113450-0700",
            "lon": -123.092225973,
            "lat": 49.2616177851
          },
          {
            "time": "20160328T113511-0700",
            "lon": -123.091800785,
            "lat": 49.2616274689
          },
          {
            "time": "20160328T113537-0700",
            "lon": -123.091299279,
            "lat": 49.2616423027
          },
          {
            "time": "20160328T113614-0700",
            "lon": -123.0904545966,
            "lat": 49.261684886
          },
          {
            "time": "20160328T113635-0700",
            "lon": -123.0900120899,
            "lat": 49.2617407913
          },
          {
            "time": "20160328T113708-0700",
            "lon": -123.0894712222,
            "lat": 49.261882591
          },
          {
            "time": "20160328T113729-0700",
            "lon": -123.0892476307,
            "lat": 49.2621284088
          },
          {
            "time": "20160328T113756-0700",
            "lon": -123.0890801939,
            "lat": 49.2623946294
          },
          {
            "time": "20160328T114129-0700",
            "lon": -123.0861101809,
            "lat": 49.262475691
          },
          {
            "time": "20160328T114147-0700",
            "lon": -123.0860160635,
            "lat": 49.2624839541
          },
          {
            "time": "20160328T114207-0700",
            "lon": -123.085948276,
            "lat": 49.2626381458
          }
        ],
        "steps": 1297,
        "endTime": "20160328T114207-0700",
        "group": "walking",
        "activity": "walking"
      }],
      "endTime": "20160328T114207-0700",
      "type": "move"
    },
    {
      "startTime": "20160328T114207-0700",
      "lastUpdate": "20160329T003011Z",
      "activities": [{
        "startTime": "20160328T114228-0700",
        "manual": false,
        "distance": 191,
        "duration": 162,
        "trackPoints": [],
        "steps": 255,
        "endTime": "20160328T114510-0700",
        "group": "walking",
        "activity": "walking"
      }],
      "place": {
        "id": 92450218,
        "location": {
          "lon": -123.085948276,
          "lat": 49.2626381458
        },
        "name": "Lori house ",
        "type": "home"
      },
      "endTime": "20160328T120150-0700",
      "type": "place"
    },
    {
      "startTime": "20160328T120150-0700",
      "lastUpdate": "20160329T003011Z",
      "activities": [{
        "startTime": "20160328T120150-0700",
        "manual": false,
        "distance": 13471,
        "duration": 1237,
        "trackPoints": [
          {
            "time": "20160328T120150-0700",
            "lon": -123.085948276,
            "lat": 49.2626381458
          },
          {
            "time": "20160328T120211-0700",
            "lon": -123.0851166591,
            "lat": 49.262943647
          },
          {
            "time": "20160328T120231-0700",
            "lon": -123.0840899858,
            "lat": 49.263315629
          },
          {
            "time": "20160328T120301-0700",
            "lon": -123.0814660747,
            "lat": 49.2638730341
          },
          {
            "time": "20160328T120336-0700",
            "lon": -123.0797102669,
            "lat": 49.2651336555
          },
          {
            "time": "20160328T120435-0700",
            "lon": -123.0772826407,
            "lat": 49.2688518958
          },
          {
            "time": "20160328T120455-0700",
            "lon": -123.0772829323,
            "lat": 49.2695200714
          },
          {
            "time": "20160328T120536-0700",
            "lon": -123.0773366639,
            "lat": 49.2698981435
          },
          {
            "time": "20160328T120557-0700",
            "lon": -123.0773110439,
            "lat": 49.2725508798
          },
          {
            "time": "20160328T120617-0700",
            "lon": -123.0773057707,
            "lat": 49.2751505061
          },
          {
            "time": "20160328T120649-0700",
            "lon": -123.0771896509,
            "lat": 49.2788631844
          },
          {
            "time": "20160328T120735-0700",
            "lon": -123.0770374595,
            "lat": 49.2809815281
          },
          {
            "time": "20160328T120801-0700",
            "lon": -123.074397663,
            "lat": 49.2812527682
          },
          {
            "time": "20160328T120822-0700",
            "lon": -123.071485743,
            "lat": 49.2812285026
          },
          {
            "time": "20160328T120859-0700",
            "lon": -123.0672018868,
            "lat": 49.2810458063
          },
          {
            "time": "20160328T120919-0700",
            "lon": -123.0662766497,
            "lat": 49.2810066754
          },
          {
            "time": "20160328T120944-0700",
            "lon": -123.0622874144,
            "lat": 49.2811854972
          },
          {
            "time": "20160328T121000-0700",
            "lon": -123.0597632968,
            "lat": 49.2811852337
          },
          {
            "time": "20160328T121016-0700",
            "lon": -123.056890897,
            "lat": 49.2812094907
          },
          {
            "time": "20160328T121051-0700",
            "lon": -123.0545392726,
            "lat": 49.2811219498
          },
          {
            "time": "20160328T121109-0700",
            "lon": -123.0521107735,
            "lat": 49.2810932455
          },
          {
            "time": "20160328T121405-0700",
            "lon": -123.0444435834,
            "lat": 49.2848403024
          },
          {
            "time": "20160328T121422-0700",
            "lon": -123.0439718247,
            "lat": 49.2847822493
          },
          {
            "time": "20160328T121440-0700",
            "lon": -123.0440251052,
            "lat": 49.2861838034
          },
          {
            "time": "20160328T121501-0700",
            "lon": -123.0441609092,
            "lat": 49.2883597251
          },
          {
            "time": "20160328T121519-0700",
            "lon": -123.0440069948,
            "lat": 49.2885723858
          },
          {
            "time": "20160328T121621-0700",
            "lon": -123.0299337149,
            "lat": 49.2884425688
          },
          {
            "time": "20160328T121718-0700",
            "lon": -123.0264454983,
            "lat": 49.2971940386
          },
          {
            "time": "20160328T121733-0700",
            "lon": -123.0264361494,
            "lat": 49.3003238208
          },
          {
            "time": "20160328T121751-0700",
            "lon": -123.026669492,
            "lat": 49.3038407581
          },
          {
            "time": "20160328T121819-0700",
            "lon": -123.0277916793,
            "lat": 49.3087890739
          },
          {
            "time": "20160328T121904-0700",
            "lon": -123.0358677557,
            "lat": 49.3148719801
          },
          {
            "time": "20160328T121930-0700",
            "lon": -123.0360882152,
            "lat": 49.3171425246
          },
          {
            "time": "20160328T122000-0700",
            "lon": -123.0375933541,
            "lat": 49.320027275
          },
          {
            "time": "20160328T122018-0700",
            "lon": -123.0382941792,
            "lat": 49.3222129575
          },
          {
            "time": "20160328T122042-0700",
            "lon": -123.038241166,
            "lat": 49.3254667401
          },
          {
            "time": "20160328T122125-0700",
            "lon": -123.0378985068,
            "lat": 49.3312104107
          },
          {
            "time": "20160328T122201-0700",
            "lon": -123.0378360655,
            "lat": 49.333561843
          },
          {
            "time": "20160328T122227-0700",
            "lon": -123.0380735072,
            "lat": 49.3365118866
          }
        ],
        "endTime": "20160328T122227-0700",
        "group": "transport",
        "activity": "transport"
      }],
      "endTime": "20160328T122227-0700",
      "type": "move"
    },
    {
      "startTime": "20160328T122227-0700",
      "lastUpdate": "20160329T003011Z",
      "activities": [{
        "startTime": "20160328T122325-0700",
        "manual": false,
        "distance": 48,
        "duration": 95,
        "trackPoints": [],
        "steps": 81,
        "endTime": "20160328T122500-0700",
        "group": "walking",
        "activity": "walking"
      }],
      "place": {
        "id": 257343109,
        "location": {
          "lon": -123.0380735072,
          "lat": 49.3365118866
        },
        "type": "unknown"
      },
      "endTime": "20160328T123004-0700",
      "type": "place"
    },
    {
      "startTime": "20160328T123004-0700",
      "lastUpdate": "20160329T003011Z",
      "activities": [{
        "startTime": "20160328T123004-0700",
        "manual": false,
        "distance": 2556,
        "duration": 510,
        "trackPoints": [
          {
            "time": "20160328T123004-0700",
            "lon": -123.0380735072,
            "lat": 49.3365118866
          },
          {
            "time": "20160328T123038-0700",
            "lon": -123.038078203,
            "lat": 49.3366192676
          },
          {
            "time": "20160328T123055-0700",
            "lon": -123.0380768339,
            "lat": 49.33662835
          },
          {
            "time": "20160328T123126-0700",
            "lon": -123.0380648073,
            "lat": 49.3366703572
          },
          {
            "time": "20160328T123147-0700",
            "lon": -123.0376384995,
            "lat": 49.3373999234
          },
          {
            "time": "20160328T123225-0700",
            "lon": -123.0312669067,
            "lat": 49.3406953013
          },
          {
            "time": "20160328T123243-0700",
            "lon": -123.0290486064,
            "lat": 49.3417341941
          },
          {
            "time": "20160328T123317-0700",
            "lon": -123.0243009794,
            "lat": 49.3417369845
          },
          {
            "time": "20160328T123337-0700",
            "lon": -123.0219883934,
            "lat": 49.3415273323
          },
          {
            "time": "20160328T123409-0700",
            "lon": -123.0209021796,
            "lat": 49.341725633
          },
          {
            "time": "20160328T123541-0700",
            "lon": -123.0188096518,
            "lat": 49.343241942
          },
          {
            "time": "20160328T123834-0700",
            "lon": -123.0194957145,
            "lat": 49.338449706
          }
        ],
        "endTime": "20160328T123834-0700",
        "group": "transport",
        "activity": "transport"
      }],
      "endTime": "20160328T123834-0700",
      "type": "move"
    },
    {
      "startTime": "20160328T123834-0700",
      "lastUpdate": "20160329T003011Z",
      "place": {
        "id": 257343110,
        "location": {
          "lon": -123.0194957145,
          "lat": 49.338449706
        },
        "type": "unknown"
      },
      "endTime": "20160328T125040-0700",
      "type": "place"
    },
    {
      "startTime": "20160328T125040-0700",
      "lastUpdate": "20160329T003011Z",
      "activities": [{
        "startTime": "20160328T125040-0700",
        "manual": false,
        "distance": 825,
        "duration": 639,
        "trackPoints": [
          {
            "time": "20160328T125040-0700",
            "lon": -123.0194957145,
            "lat": 49.338449706
          },
          {
            "time": "20160328T125331-0700",
            "lon": -123.0203963625,
            "lat": 49.3400840693
          },
          {
            "time": "20160328T125357-0700",
            "lon": -123.0204775965,
            "lat": 49.3400853071
          },
          {
            "time": "20160328T125439-0700",
            "lon": -123.0206961053,
            "lat": 49.3400868019
          },
          {
            "time": "20160328T125514-0700",
            "lon": -123.0185338576,
            "lat": 49.3412417453
          },
          {
            "time": "20160328T125536-0700",
            "lon": -123.0188335054,
            "lat": 49.3412670578
          },
          {
            "time": "20160328T125556-0700",
            "lon": -123.0187287602,
            "lat": 49.3414608665
          },
          {
            "time": "20160328T125612-0700",
            "lon": -123.0185858067,
            "lat": 49.3416354593
          },
          {
            "time": "20160328T125628-0700",
            "lon": -123.0184137475,
            "lat": 49.3418701179
          },
          {
            "time": "20160328T125649-0700",
            "lon": -123.0182687099,
            "lat": 49.3421134386
          },
          {
            "time": "20160328T125803-0700",
            "lon": -123.0177076682,
            "lat": 49.3427746557
          },
          {
            "time": "20160328T125819-0700",
            "lon": -123.0176480897,
            "lat": 49.3428609236
          },
          {
            "time": "20160328T125959-0700",
            "lon": -123.0175685625,
            "lat": 49.3430097962
          },
          {
            "time": "20160328T130000-0700",
            "lon": -123.0175685546,
            "lat": 49.3430098109
          },
          {
            "time": "20160328T130118-0700",
            "lon": -123.0175062612,
            "lat": 49.3431264223
          }
        ],
        "steps": 1183,
        "endTime": "20160328T130119-0700",
        "group": "walking",
        "activity": "walking"
      }],
      "endTime": "20160328T130118-0700",
      "type": "move"
    },
    {
      "startTime": "20160328T130119-0700",
      "lastUpdate": "20160329T003011Z",
      "activities": [{
        "startTime": "20160328T130119-0700",
        "manual": false,
        "distance": 288,
        "duration": 217,
        "trackPoints": [],
        "steps": 384,
        "endTime": "20160328T130456-0700",
        "group": "walking",
        "activity": "walking"
      }],
      "place": {
        "id": 257343111,
        "location": {
          "lon": -123.0175062612,
          "lat": 49.3431264223
        },
        "type": "unknown"
      },
      "endTime": "20160328T130644-0700",
      "type": "place"
    },
    {
      "startTime": "20160328T130644-0700",
      "lastUpdate": "20160329T003011Z",
      "activities": [{
        "startTime": "20160328T130644-0700",
        "manual": false,
        "distance": 726,
        "duration": 881,
        "trackPoints": [
          {
            "time": "20160328T130644-0700",
            "lon": -123.0175062612,
            "lat": 49.3431264223
          },
          {
            "time": "20160328T131342-0700",
            "lon": -123.017341149,
            "lat": 49.3441279873
          },
          {
            "time": "20160328T131915-0700",
            "lon": -123.017341149,
            "lat": 49.3441279873
          },
          {
            "time": "20160328T132124-0700",
            "lon": -123.018456673,
            "lat": 49.345477878
          }
        ],
        "steps": 1452,
        "endTime": "20160328T132125-0700",
        "group": "walking",
        "activity": "walking"
      }],
      "endTime": "20160328T132124-0700",
      "type": "move"
    },
    {
      "startTime": "20160328T132125-0700",
      "lastUpdate": "20160329T003011Z",
      "activities": [{
        "startTime": "20160328T132125-0700",
        "manual": false,
        "distance": 533,
        "duration": 471,
        "trackPoints": [],
        "steps": 711,
        "endTime": "20160328T132916-0700",
        "group": "walking",
        "activity": "walking"
      }],
      "place": {
        "id": 257343112,
        "location": {
          "lon": -123.018456673,
          "lat": 49.345477878
        },
        "type": "unknown"
      },
      "endTime": "20160328T133250-0700",
      "type": "place"
    },
    {
      "startTime": "20160328T133250-0700",
      "lastUpdate": "20160329T003011Z",
      "activities": [{
        "startTime": "20160328T133250-0700",
        "manual": false,
        "distance": 846,
        "duration": 714,
        "trackPoints": [
          {
            "time": "20160328T133250-0700",
            "lon": -123.018456673,
            "lat": 49.345477878
          },
          {
            "time": "20160328T133940-0700",
            "lon": -123.0189363913,
            "lat": 49.3497427526
          },
          {
            "time": "20160328T134000-0700",
            "lon": -123.0184819965,
            "lat": 49.3498114109
          },
          {
            "time": "20160328T134335-0700",
            "lon": -123.0160486013,
            "lat": 49.3505331219
          },
          {
            "time": "20160328T134443-0700",
            "lon": -123.0159147472,
            "lat": 49.350812974
          }
        ],
        "steps": 1110,
        "endTime": "20160328T134444-0700",
        "group": "walking",
        "activity": "walking"
      }],
      "endTime": "20160328T134443-0700",
      "type": "move"
    },
    {
      "startTime": "20160328T134444-0700",
      "lastUpdate": "20160329T003011Z",
      "activities": [{
        "startTime": "20160328T134444-0700",
        "manual": false,
        "distance": 270,
        "duration": 250,
        "trackPoints": [],
        "steps": 360,
        "endTime": "20160328T134854-0700",
        "group": "walking",
        "activity": "walking"
      }],
      "place": {
        "id": 257343113,
        "location": {
          "lon": -123.0159147472,
          "lat": 49.350812974
        },
        "type": "unknown"
      },
      "endTime": "20160328T135529-0700",
      "type": "place"
    },
    {
      "startTime": "20160328T135529-0700",
      "lastUpdate": "20160329T003011Z",
      "activities": [{
        "startTime": "20160328T135529-0700",
        "manual": false,
        "distance": 671,
        "duration": 694,
        "trackPoints": [
          {
            "time": "20160328T135529-0700",
            "lon": -123.0159147472,
            "lat": 49.350812974
          },
          {
            "time": "20160328T135959-0700",
            "lon": -123.0156555068,
            "lat": 49.3532548303
          },
          {
            "time": "20160328T140000-0700",
            "lon": -123.0156554972,
            "lat": 49.3532549208
          },
          {
            "time": "20160328T140327-0700",
            "lon": -123.0154559164,
            "lat": 49.3551348263
          },
          {
            "time": "20160328T140703-0700",
            "lon": -123.0156820641,
            "lat": 49.35572974
          }
        ],
        "steps": 1171,
        "endTime": "20160328T140703-0700",
        "group": "walking",
        "activity": "walking"
      }],
      "endTime": "20160328T140703-0700",
      "type": "move"
    },
    {
      "startTime": "20160328T140703-0700",
      "lastUpdate": "20160329T003011Z",
      "activities": [{
        "startTime": "20160328T140703-0700",
        "manual": false,
        "distance": 28,
        "duration": 35,
        "trackPoints": [],
        "steps": 57,
        "endTime": "20160328T140738-0700",
        "group": "walking",
        "activity": "walking"
      }],
      "place": {
        "id": 257356701,
        "location": {
          "lon": -123.0156820641,
          "lat": 49.35572974
        },
        "type": "unknown"
      },
      "endTime": "20160328T141333-0700",
      "type": "place"
    },
    {
      "startTime": "20160328T141333-0700",
      "lastUpdate": "20160329T003011Z",
      "activities": [{
        "startTime": "20160328T141333-0700",
        "manual": false,
        "distance": 936,
        "duration": 1054,
        "trackPoints": [
          {
            "time": "20160328T141333-0700",
            "lon": -123.0156820641,
            "lat": 49.35572974
          },
          {
            "time": "20160328T141514-0700",
            "lon": -123.0156820641,
            "lat": 49.35572974
          },
          {
            "time": "20160328T142212-0700",
            "lon": -123.0122162039,
            "lat": 49.3584233469
          },
          {
            "time": "20160328T142548-0700",
            "lon": -123.0124633407,
            "lat": 49.3572613275
          },
          {
            "time": "20160328T143007-0700",
            "lon": -123.0135753422,
            "lat": 49.3561038771
          },
          {
            "time": "20160328T143106-0700",
            "lon": -123.0135845151,
            "lat": 49.3559147286
          }
        ],
        "steps": 1871,
        "endTime": "20160328T143107-0700",
        "group": "walking",
        "activity": "walking"
      }],
      "endTime": "20160328T143106-0700",
      "type": "move"
    },
    {
      "startTime": "20160328T143107-0700",
      "lastUpdate": "20160329T003011Z",
      "place": {
        "id": 257356702,
        "location": {
          "lon": -123.0135845151,
          "lat": 49.3559147286
        },
        "type": "unknown"
      },
      "endTime": "20160328T143207-0700",
      "type": "place"
    },
    {
      "startTime": "20160328T143207-0700",
      "lastUpdate": "20160329T003011Z",
      "activities": [
        {
          "startTime": "20160328T143207-0700",
          "manual": false,
          "distance": 2341,
          "duration": 2848,
          "trackPoints": [
            {
              "time": "20160328T143207-0700",
              "lon": -123.0135845151,
              "lat": 49.3559147286
            },
            {
              "time": "20160328T143353-0700",
              "lon": -123.0135754315,
              "lat": 49.3558320484
            },
            {
              "time": "20160328T143754-0700",
              "lon": -123.0144823372,
              "lat": 49.3551327719
            },
            {
              "time": "20160328T143829-0700",
              "lon": -123.0144843001,
              "lat": 49.3550513319
            },
            {
              "time": "20160328T144137-0700",
              "lon": -123.0151802717,
              "lat": 49.3542635936
            },
            {
              "time": "20160328T144152-0700",
              "lon": -123.0152205419,
              "lat": 49.3542057901
            },
            {
              "time": "20160328T144924-0700",
              "lon": -123.0158603412,
              "lat": 49.3513858492
            },
            {
              "time": "20160328T145023-0700",
              "lon": -123.0158665137,
              "lat": 49.3513548798
            },
            {
              "time": "20160328T145711-0700",
              "lon": -123.0176536252,
              "lat": 49.3480064132
            },
            {
              "time": "20160328T145959-0700",
              "lon": -123.0172598456,
              "lat": 49.3473392557
            },
            {
              "time": "20160328T150000-0700",
              "lon": -123.0172598222,
              "lat": 49.3473392161
            },
            {
              "time": "20160328T150049-0700",
              "lon": -123.0171444721,
              "lat": 49.3471437853
            },
            {
              "time": "20160328T150433-0700",
              "lon": -123.0173470551,
              "lat": 49.3457257747
            },
            {
              "time": "20160328T150710-0700",
              "lon": -123.017383124,
              "lat": 49.3456287554
            },
            {
              "time": "20160328T151248-0700",
              "lon": -123.0183682142,
              "lat": 49.3426525626
            },
            {
              "time": "20160328T151649-0700",
              "lon": -123.018935333,
              "lat": 49.3403490138
            },
            {
              "time": "20160328T151747-0700",
              "lon": -123.018935333,
              "lat": 49.3403490138
            },
            {
              "time": "20160328T151934-0700",
              "lon": -123.0189742282,
              "lat": 49.3401235796
            }
          ],
          "steps": 4683,
          "endTime": "20160328T151935-0700",
          "group": "walking",
          "activity": "walking"
        },
        {
          "startTime": "20160328T151934-0700",
          "manual": false,
          "distance": 13712,
          "duration": 1968,
          "trackPoints": [
            {
              "time": "20160328T151934-0700",
              "lon": -123.0189742282,
              "lat": 49.3401235796
            },
            {
              "time": "20160328T152122-0700",
              "lon": -123.0192661821,
              "lat": 49.3384314316
            },
            {
              "time": "20160328T152146-0700",
              "lon": -123.019372319,
              "lat": 49.3383314533
            },
            {
              "time": "20160328T152244-0700",
              "lon": -123.0196245017,
              "lat": 49.3377194032
            },
            {
              "time": "20160328T152411-0700",
              "lon": -123.021201341,
              "lat": 49.3365404577
            },
            {
              "time": "20160328T152456-0700",
              "lon": -123.0239144689,
              "lat": 49.3359120311
            },
            {
              "time": "20160328T152517-0700",
              "lon": -123.0251798475,
              "lat": 49.335927348
            },
            {
              "time": "20160328T152542-0700",
              "lon": -123.0261628586,
              "lat": 49.3358708824
            },
            {
              "time": "20160328T152612-0700",
              "lon": -123.0290370055,
              "lat": 49.3359701274
            },
            {
              "time": "20160328T152632-0700",
              "lon": -123.0315917786,
              "lat": 49.3361327068
            },
            {
              "time": "20160328T152710-0700",
              "lon": -123.0349290341,
              "lat": 49.3362382643
            },
            {
              "time": "20160328T152751-0700",
              "lon": -123.0380110528,
              "lat": 49.3357559876
            },
            {
              "time": "20160328T152833-0700",
              "lon": -123.0380871732,
              "lat": 49.3335342703
            },
            {
              "time": "20160328T152859-0700",
              "lon": -123.0379823229,
              "lat": 49.3326378939
            },
            {
              "time": "20160328T152914-0700",
              "lon": -123.0380763724,
              "lat": 49.330634638
            },
            {
              "time": "20160328T152936-0700",
              "lon": -123.0381984089,
              "lat": 49.3282505005
            },
            {
              "time": "20160328T153017-0700",
              "lon": -123.0382387169,
              "lat": 49.3234864674
            },
            {
              "time": "20160328T153051-0700",
              "lon": -123.0371157842,
              "lat": 49.3192825522
            },
            {
              "time": "20160328T153119-0700",
              "lon": -123.036755615,
              "lat": 49.3160387798
            },
            {
              "time": "20160328T153211-0700",
              "lon": -123.0346673517,
              "lat": 49.3132869752
            },
            {
              "time": "20160328T153241-0700",
              "lon": -123.0346673517,
              "lat": 49.3132869752
            },
            {
              "time": "20160328T153310-0700",
              "lon": -123.0329885301,
              "lat": 49.313248816
            },
            {
              "time": "20160328T153359-0700",
              "lon": -123.0321776161,
              "lat": 49.3092001245
            },
            {
              "time": "20160328T153418-0700",
              "lon": -123.0320092804,
              "lat": 49.3074671098
            },
            {
              "time": "20160328T153452-0700",
              "lon": -123.031521112,
              "lat": 49.3050648083
            },
            {
              "time": "20160328T153537-0700",
              "lon": -123.0275851834,
              "lat": 49.3016058343
            },
            {
              "time": "20160328T153705-0700",
              "lon": -123.0267901468,
              "lat": 49.2925350708
            },
            {
              "time": "20160328T154025-0700",
              "lon": -123.050853292,
              "lat": 49.2886322834
            },
            {
              "time": "20160328T154122-0700",
              "lon": -123.0563882699,
              "lat": 49.2873064351
            },
            {
              "time": "20160328T154148-0700",
              "lon": -123.0566967375,
              "lat": 49.2868595222
            },
            {
              "time": "20160328T154527-0700",
              "lon": -123.0659736285,
              "lat": 49.2839582347
            },
            {
              "time": "20160328T154929-0700",
              "lon": -123.0696002847,
              "lat": 49.271533
            },
            {
              "time": "20160328T155222-0700",
              "lon": -123.0702902457,
              "lat": 49.2643226903
            }
          ],
          "endTime": "20160328T155222-0700",
          "group": "transport",
          "activity": "transport"
        },
        {
          "startTime": "20160328T155222-0700",
          "manual": false,
          "distance": 133,
          "duration": 228,
          "trackPoints": [
            {
              "time": "20160328T155222-0700",
              "lon": -123.0702902457,
              "lat": 49.2643226903
            },
            {
              "time": "20160328T155250-0700",
              "lon": -123.0703053667,
              "lat": 49.2641646704
            },
            {
              "time": "20160328T155307-0700",
              "lon": -123.0703037912,
              "lat": 49.264099858
            },
            {
              "time": "20160328T155609-0700",
              "lon": -123.0701411888,
              "lat": 49.2642291356
            }
          ],
          "steps": 266,
          "endTime": "20160328T155610-0700",
          "group": "walking",
          "activity": "walking"
        }
      ],
      "endTime": "20160328T155609-0700",
      "type": "move"
    },
    {
      "startTime": "20160328T155610-0700",
      "lastUpdate": "20160329T003011Z",
      "activities": [
        {
          "startTime": "20160328T155619-0700",
          "manual": false,
          "distance": 34,
          "duration": 50,
          "trackPoints": [],
          "steps": 67,
          "endTime": "20160328T155709-0700",
          "group": "walking",
          "activity": "walking"
        },
        {
          "startTime": "20160328T160012-0700",
          "manual": false,
          "distance": 272,
          "duration": 219,
          "trackPoints": [],
          "steps": 363,
          "endTime": "20160328T160351-0700",
          "group": "walking",
          "activity": "walking"
        }
      ],
      "place": {
        "id": 257367234,
        "location": {
          "lon": -123.0701411888,
          "lat": 49.2642291356
        },
        "type": "unknown"
      },
      "endTime": "20160328T161342-0700",
      "type": "place"
    },
    {
      "startTime": "20160328T161342-0700",
      "lastUpdate": "20160329T003011Z",
      "activities": [
        {
          "startTime": "20160328T161342-0700",
          "manual": false,
          "distance": 2350,
          "duration": 321,
          "trackPoints": [
            {
              "time": "20160328T161342-0700",
              "lon": -123.0701411888,
              "lat": 49.2642291356
            },
            {
              "time": "20160328T161446-0700",
              "lon": -123.0739018258,
              "lat": 49.2625411111
            },
            {
              "time": "20160328T161528-0700",
              "lon": -123.0771373428,
              "lat": 49.2624503143
            },
            {
              "time": "20160328T161548-0700",
              "lon": -123.0786618033,
              "lat": 49.2624127254
            },
            {
              "time": "20160328T161631-0700",
              "lon": -123.0866212787,
              "lat": 49.2624863822
            },
            {
              "time": "20160328T161704-0700",
              "lon": -123.0900507057,
              "lat": 49.262469745
            },
            {
              "time": "20160328T161725-0700",
              "lon": -123.0912904522,
              "lat": 49.2624431759
            },
            {
              "time": "20160328T161747-0700",
              "lon": -123.0950910392,
              "lat": 49.262535933
            },
            {
              "time": "20160328T161808-0700",
              "lon": -123.0957277875,
              "lat": 49.262556695
            },
            {
              "time": "20160328T161830-0700",
              "lon": -123.096652845,
              "lat": 49.2624850684
            },
            {
              "time": "20160328T161903-0700",
              "lon": -123.0974701904,
              "lat": 49.2625960648
            }
          ],
          "endTime": "20160328T161903-0700",
          "group": "transport",
          "activity": "transport"
        },
        {
          "startTime": "20160328T161903-0700",
          "manual": false,
          "distance": 166,
          "duration": 193,
          "trackPoints": [
            {
              "time": "20160328T161903-0700",
              "lon": -123.0974701904,
              "lat": 49.2625960648
            },
            {
              "time": "20160328T161925-0700",
              "lon": -123.0974824963,
              "lat": 49.2625905317
            },
            {
              "time": "20160328T161941-0700",
              "lon": -123.0975109661,
              "lat": 49.2624746203
            },
            {
              "time": "20160328T162012-0700",
              "lon": -123.0975449658,
              "lat": 49.2623776905
            },
            {
              "time": "20160328T162033-0700",
              "lon": -123.0975537596,
              "lat": 49.2623586366
            },
            {
              "time": "20160328T162053-0700",
              "lon": -123.0975575842,
              "lat": 49.2623558113
            },
            {
              "time": "20160328T162135-0700",
              "lon": -123.0975637173,
              "lat": 49.2623492114
            },
            {
              "time": "20160328T162155-0700",
              "lon": -123.097564008,
              "lat": 49.2623470441
            },
            {
              "time": "20160328T162216-0700",
              "lon": -123.0976976188,
              "lat": 49.2624057934
            }
          ],
          "steps": 332,
          "endTime": "20160328T162216-0700",
          "group": "walking",
          "activity": "walking"
        }
      ],
      "endTime": "20160328T162216-0700",
      "type": "move"
    },
    {
      "startTime": "20160328T162216-0700",
      "lastUpdate": "20160329T003011Z",
      "activities": [{
        "startTime": "20160328T162446-0700",
        "manual": false,
        "distance": 187,
        "duration": 170,
        "trackPoints": [],
        "steps": 249,
        "endTime": "20160328T162736-0700",
        "group": "walking",
        "activity": "walking"
      }],
      "place": {
        "id": 9141978,
        "location": {
          "lon": -123.09769761882858,
          "lat": 49.26240579342952
        },
        "name": "Kingsgate Mall",
        "foursquareId": "4b3289f6f964a520190e25e3",
        "type": "foursquare"
      },
      "endTime": "20160328T163314-0700",
      "type": "place"
    },
    {
      "startTime": "20160328T163314-0700",
      "lastUpdate": "20160329T162415Z",
      "activities": [
        {
          "startTime": "20160328T163346-0700",
          "manual": false,
          "distance": 88,
          "duration": 105,
          "trackPoints": [],
          "steps": 176,
          "endTime": "20160328T163531-0700",
          "group": "walking",
          "activity": "walking"
        },
        {
          "startTime": "20160328T171812-0700",
          "manual": false,
          "distance": 15,
          "duration": 30,
          "trackPoints": [],
          "steps": 30,
          "endTime": "20160328T171842-0700",
          "group": "walking",
          "activity": "walking"
        },
        {
          "startTime": "20160328T202417-0700",
          "manual": false,
          "distance": 21,
          "duration": 31,
          "trackPoints": [],
          "steps": 41,
          "endTime": "20160328T202448-0700",
          "group": "walking",
          "activity": "walking"
        },
        {
          "startTime": "20160328T234357-0700",
          "manual": false,
          "distance": 18,
          "duration": 26,
          "trackPoints": [],
          "steps": 37,
          "endTime": "20160328T234423-0700",
          "group": "walking",
          "activity": "walking"
        }
      ],
      "place": {
        "id": 52989451,
        "location": {
          "lon": -123.0955654948,
          "lat": 49.2609911813
        },
        "name": "Home",
        "type": "home"
      },
      "endTime": "20160329T085010-0700",
      "type": "place"
    }
  ],
  "lastUpdate": "20160329T162415Z",
  "date": "20160328"
}]
